ludere/__init__.py
ludere/core.py
ludere/reflection.py
ludere-0.3.0.dist-info/LICENSE
ludere-0.3.0.dist-info/WHEEL
ludere-0.3.0.dist-info/METADATA
ludere-0.3.0.dist-info/RECORD
