Metadata-Version: 2.1
Name: ludere
Version: 0.3.0
Summary: Toy DI framework
Author: Vlad Smirnov
Author-email: gnudeb0@gmail.com
Requires-Python: >=3.8,<4.0
Classifier: Programming Language :: Python :: 3
Classifier: Programming Language :: Python :: 3.8
Classifier: Programming Language :: Python :: 3.9
